[
    {
        "Question": "Is the character Gurukant \"Guru\" Desai in the movie \"Guru\" (2006) based on someone other than Dhirubhai Ambani?",
        "Answer": "NO"
    },
    {
        "Question": "Is the movie \"Guru\" (2006) inspired by the life of Dhirubhai Ambani?",
        "Answer": "YES"
    },
    {
        "Question": "Is Sujata \"Suju\" Desai in the movie \"Guru\" (2006) based on a fictional character and not inspired by Kokilaben Ambani?",
        "Answer": "NO"
    },
    {
        "Question": "Is Sujata \"Suju\" Desai in the movie \"Guru\" (2006) based on Kokilaben Ambani?",
        "Answer": "YES"
    },
    {
        "Question": "Is Mithun Chakraborty the only character in the movie \"Guru\" released in 2006 who is based on Pannalal Dasgupta?",
        "Answer": "NO"
    },
    {
        "Question": "Is \"Nanaji\" Manik Dasgupta, played by Mithun Chakraborty, inspired by Pannalal Dasgupta in the movie \"Guru\" released in 2006?",
        "Answer": "YES"
    },
    {
        "Question": "Is Shyam Saxena in the movie Guru from 2006 not based on Swaminathan Gurumurthy?",
        "Answer": "NO"
    },
    {
        "Question": "Is Shyam Saxena in the movie Guru from 2006 based on Swaminathan Gurumurthy?",
        "Answer": "YES"
    },
    {
        "Question": "Is the character Meenakshi \"Meenu\" Saxena in the movie \"Guru\" (2006) based on Vidya Balan?",
        "Answer": "NO"
    },
    {
        "Question": "Is Gupta a character related to Meenakshi \"Meenu\" Saxena in the movie \"Guru\" (2006)?",
        "Answer": "YES"
    },
    {
        "Question": "Did Mallika Sherawat play a character other than Champa in the movie \"Guru\" released in 2006?",
        "Answer": "NO"
    },
    {
        "Question": "Is Champa a dancer in the song \"Mayya Mayya\" in the movie \"Guru\" released in 2006?",
        "Answer": "YES"
    },
    {
        "Question": "Is Jignesh in the movie \"Guru\" (2006) based on Arya Babbar?",
        "Answer": "NO"
    },
    {
        "Question": "Is Jignesh in the movie \"Guru\" (2006) based on Champaklal Damani?",
        "Answer": "YES"
    },
    {
        "Question": "Is the character Arzan Contractor in the movie \"Guru\" (2006) based on anyone other than Ratan Tata?",
        "Answer": "NO"
    },
    {
        "Question": "Is Arzan Contractor, played by Arjan Bajwa, based on Ratan Tata in the movie \"Guru\" (2006)?",
        "Answer": "YES"
    },
    {
        "Question": "Is the character Contractor in the movie \"Guru\" (2006) based on someone other than Naval Tata?",
        "Answer": "NO"
    },
    {
        "Question": "Is the character Contractor in the movie \"Guru\" (2006) portrayed by Dhritiman Chatterjee?",
        "Answer": "YES"
    }
]