[
  {
    "Question": "In the 2018 movie 'Race 3', which character is portrayed by Anil Kapoor?",
    "Options": "A. Shamsher Singh\nB. Sikandar Singh\nC. Jessica Singh\nD. Ranvir Singh",
    "Answer": "Shamsher Singh"
  },
  {
    "Question": "In the movie 'Race 3', released in 2018, which character is portrayed by Salman Khan?",
    "Options": "A. Sikander Singh\nB. Rohit\nC. Shivani\nD. Ramesh",
    "Answer": "Sikander Singh"
  },
  {
    "Question": "In the 2018 movie 'Race 3', which character is portrayed by Bobby Deol?",
    "Options": "A. Yash Singh\nB. Armaan Malik\nC. Shamsher Singh\nD. Sikander Singh",
    "Answer": "Yash Singh"
  },
  {
    "Question": "In the movie 'Race 3' (2018), which character does Jacqueline Fernandez portray?",
    "Options": "A. Sikander\nB. Jessica Gomes\nC. Shamsher\nD. Ranvir",
    "Answer": "Jessica Gomes"
  },
  {
    "Question": "In the movie 'Race 3' released in 2018, which actress plays the role of Sanjana Singh?",
    "Options": "A. Daisy Shah\nB. Jacqueline Fernandez\nC. Anil Kapoor\nD. Saif Ali Khan",
    "Answer": "Daisy Shah"
  },
  {
    "Question": "In the 2018 movie 'Race 3', which character is portrayed by Saqib Saleem?",
    "Options": "A. Saqib Singh\nB. Suraj Singh\nC. Rajveer Singh\nD. Shamsher Singh",
    "Answer": "Suraj Singh"
  },
  {
    "Question": "In the movie 'Race 3' (2018), which character is portrayed by Sharat Saxena?",
    "Options": "A. Raghuvendra Sinha\nB. Ranvir Singh\nC. Shamsher Singh\nD. Sikandar Singh",
    "Answer": "Raghuvendra Sinha"
  },
  {
    "Question": "In the 2018 movie 'Race 3', which character does Freddy Daruwala portray in relation to Shamsher?",
    "Options": "A. A. Shamsher's ally\nB. B. Shamsher's enemy and later partner\nC. C. Shamsher's brother\nD. D. Shamsher's mentor",
    "Answer": "B. Shamsher's enemy and later partner"
  },
  {
    "Question": "In the movie 'Race 3', released in 2018, which character is portrayed by Rajesh Sharma?",
    "Options": "A. Brij Mohan\nB. Sikander\nC. Shamsher\nD. Jessica",
    "Answer": "Brij Mohan"
  },
  {
    "Question": "In the 2018 movie 'Race 3', which character is portrayed by Nishigandha Wad?",
    "Options": "A. A. Shamsher\nB. B. Ranchor's widow\nC. C. Sumitra Singh\nD. D. Race Master",
    "Answer": "C. Sumitra Singh"
  },
  {
    "Question": "In the 2018 movie 'Race 3', which character is portrayed by Milind Gunaji?",
    "Options": "A. Shamsher\nB. Ranchor Singh\nC. Sanjana\nD. Sikander",
    "Answer": "Ranchor Singh"
  },
  {
    "Question": "In the 2018 movie 'Race 3', which character is portrayed by Narendra Jha?",
    "Options": "A. Vikram Khanna\nB. Shamsher Singh\nC. Sikander Singh\nD. Jessica Singh",
    "Answer": "Vikram Khanna"
  },
  {
    "Question": "In the 2018 movie 'Race 3', which character is played by Chaitanya Kanhai?",
    "Options": "A. A. Gajendra\nB. B. Narendra Pathak\nC. C. Race\nD. D. Shamsher",
    "Answer": "B. Narendra Pathak"
  },
  {
    "Question": "In the 2018 movie 'Race 3', which character is portrayed by B. K. Tiwari?",
    "Options": "A. Gajendra Pathak\nB. Narendra\nC. Shamsher Singh\nD. Sikander",
    "Answer": "Gajendra Pathak"
  }
]