[
  {
    "Question": "In the movie 'Disaster Movie', who does Will have a romantic relationship with that encounters issues and leads to their breakup?",
    "Options": "A. Batman\nB. Will\nC. Amy\nD. Caveman",
    "Answer": "Amy"
  },
  {
    "Question": "Who is revealed to have an affair with Flavor Flav, leading to a breakup with Will in the movie *Disaster Movie*?",
    "Options": "A. Batman\nB. Will\nC. Flavor Flav\nD. Amy",
    "Answer": "Amy"
  },
  {
    "Question": "Who informs them to go to evacuation buses and warns that there will be no chance of survival if they go to save Amy?",
    "Options": "A. Batman\nB. Will\nC. Crystal Skull\nD. Amy",
    "Answer": "Batman"
  },
  {
    "Question": "Who hosts a Super Duper Sweet Sixteen party at his house, despite being 25 years old?",
    "Options": "A. Batman\nB. Will\nC. Super Duper Sweet Sixteen\nD. Amy",
    "Answer": "Will"
  },
  {
    "Question": "Who does Will admit his feelings for before the call is dropped in the movie 'Disaster Movie'?",
    "Options": "A. Batman\nB. Will\nC. Amy\nD. Evacuation Buses",
    "Answer": "Amy"
  },
  {
    "Question": "Who is revealed to be Will's father?",
    "Options": "A. Batman\nB. Will\nC. Indiana Jones\nD. Amy",
    "Answer": "Indiana Jones"
  },
  {
    "Question": "Who stabs 'Beowulf' in the back according to the plot of the movie?",
    "Options": "A. Will\nB. Amy\nC. Indiana Jones\nD. Caveman",
    "Answer": "Amy"
  },
  {
    "Question": "Who did Amy have an affair with in the movie *Disaster Movie*, leading to her breakup with Will?",
    "Options": "A. Will\nB. Amy\nC. Flavor Flav\nD. Indiana Jones",
    "Answer": "Flavor Flav"
  },
  {
    "Question": "Who encounters Indiana Jones after Amy stabs 'Beowulf' in the back?",
    "Options": "A. Will\nB. Amy\nC. Crystal Skull\nD. Indiana Jones",
    "Answer": "Will"
  },
  {
    "Question": "Who hosts a Super Duper Sweet Sixteen party at his house despite being 25 years old?",
    "Options": "A. Beowulf\nB. Will\nC. Indiana Jones\nD. Amy",
    "Answer": "Will"
  },
  {
    "Question": "Who stabs 'Beowulf' in the back before encountering Indiana Jones?",
    "Options": "A. Will\nB. Amy\nC. Indiana Jones\nD. None of the above",
    "Answer": "Amy"
  },
  {
    "Question": "Who is revealed to be Will's father in the movie 'Disaster Movie'?",
    "Options": "A. Beowulf\nB. Will\nC. Indiana Jones\nD. Amy",
    "Answer": "Indiana Jones"
  }
]