[
    {
        "Question": "Is Pritam Chakraborty the composer of the song 'Ghar More Pardesiya' from the movie Kalank?",
        "Answer": "Yes."
    },
    {
        "Question": "Did Amitabh Bhattacharya write the lyrics for the song 'Ghar More Pardesiya' from the soundtrack of Kalank?",
        "Answer": "Yes."
    },
    {
        "Question": "Is the song 'Tabaah Ho Gaye' composed by Pritam Chakraborty?",
        "Answer": "No"
    },
    {
        "Question": "Did Amitabh Bhattacharya write the lyrics for the song 'Tabaah Ho Gaye'?",
        "Answer": "Yes."
    },
    {
        "Question": "Is Pritam Chakraborty the composer of the song 'Aira Gaira' from the soundtrack of Kalank?",
        "Answer": "Yes."
    },
    {
        "Question": "Did Amitabh Bhattacharya write the lyrics for the song 'Aira Gaira' in the soundtrack of Kalank?",
        "Answer": "Yes."
    }
]