[
    {
        "Question": "Is Aditya related to Lucky Negi in any way?",
        "Answer": "No."
    },
    {
        "Question": "Is Aditya the child of a private investigator in the movie 'Lucky: No Time for Love'?",
        "Answer": "No."
    },
    {
        "Question": "Did Lucky Negi and Mr. Sekhri have a direct connection in the context of the attempted crime?",
        "Answer": "No."
    },
    {
        "Question": "Is the car owner involved in a rescue operation related to Mr. Sekhri?",
        "Answer": "Yes."
    },
    {
        "Question": "Did the terrorists pose a threat to Mr. Sekhri's family?",
        "Answer": "Yes"
    },
    {
        "Question": "Did Lucky Negi fall in love with Aditya's father, Mr. Sekhri?",
        "Answer": "No"
    },
    {
        "Question": "Is Mr. Sekhri the Indian Ambassador to Russia?",
        "Answer": "Yes."
    },
    {
        "Question": "Is Lucky in a romantic relationship with Mr. Sekhri?",
        "Answer": "No."
    },
    {
        "Question": "Did Lucky Negi and the local doctor provide help to Aditya during a dangerous situation?",
        "Answer": "Yes."
    },
    {
        "Question": "Did the local doctor assist in the rescue of the car owner?",
        "Answer": "No"
    },
    {
        "Question": "Did the local doctor provide a safe place for Lucky Negi and Aditya to hide from the terrorists?",
        "Answer": "Yes."
    },
    {
        "Question": "Did Lucky Negi fall in love with someone while visiting the local doctor's clinic?",
        "Answer": "Yes."
    },
    {
        "Question": "Did Aditya spend time in Russia after taking refuge in the local doctor's clinic?",
        "Answer": "Yes."
    },
    {
        "Question": "Did Lucky fall in love with a local doctor in the movie?",
        "Answer": "No."
    },
    {
        "Question": "Did Lucky Negi experience an attempted crime in the presence of the Colonel?",
        "Answer": "No."
    },
    {
        "Question": "Did the car owner help the colonel in reuniting with their families?",
        "Answer": "No."
    },
    {
        "Question": "Did the terrorists pose a threat to the colonel in the movie?",
        "Answer": "No."
    },
    {
        "Question": "Did Lucky Negi fall in love with Aditya during their struggle to return to their families?",
        "Answer": "Yes."
    },
    {
        "Question": "Did Aditya spend time in Russia with the Colonel?",
        "Answer": "No"
    },
    {
        "Question": "Did Lucky and the Colonel ever meet in Russia?",
        "Answer": "No."
    },
    {
        "Question": "Is Mr. Sekhri the father of Aditya?",
        "Answer": "No"
    },
    {
        "Question": "Is Mr. Negi related to Aditya in any way?",
        "Answer": "Yes."
    },
    {
        "Question": "Was Aditya a victim of an attempted crime involving a young Russian?",
        "Answer": "Yes"
    },
    {
        "Question": "Is Mr. Sekhri related to the car owner in any way?",
        "Answer": "No"
    },
    {
        "Question": "Did the car owner encounter a young Russian during his journey?",
        "Answer": "No."
    },
    {
        "Question": "Is Mr. Sekhri related to Aditya in any way?",
        "Answer": "No"
    },
    {
        "Question": "Is Mr. Negi related to Aditya in any way?",
        "Answer": "No"
    },
    {
        "Question": "Did the young Russian have a negative impact on Aditya's relationship with Lucky Negi?",
        "Answer": "Yes."
    },
    {
        "Question": "Did Aditya rescue Lucky Negi in a car?",
        "Answer": "Yes"
    },
    {
        "Question": "Did Aditya and Lucky fall in love while they were in Russia?",
        "Answer": "Yes."
    }
]