[
  {
    "Question": "What was introduced as a medium to narrate the story in the film 'Cash'?",
    "Options": "A. animation segments\nB. gold\nC. silver\nD. platinum",
    "Answer": "animation segments"
  },
  {
    "Question": "What aspect of the film 'Cash' is described as its biggest flaw?",
    "Options": "A. animation segments\nB. strong character development\nC. thin plot\nD. exceptional cinematography",
    "Answer": "thin plot"
  },
  {
    "Question": "What element was considered for inclusion in the film to enhance its appeal to the audience?",
    "Options": "A. Live action scenes\nB. Animation segments\nC. Documentary footage\nD. Musical numbers",
    "Answer": "Animation segments"
  },
  {
    "Question": "What is used as a medium to narrate the story of a diamond in the film?",
    "Options": "A. animation segments\nB. gold\nC. silver\nD. platinum",
    "Answer": "animation segments"
  },
  {
    "Question": "What is considered the biggest flaw of the film 'Cash'?",
    "Options": "A. Rich character development\nB. Innovative animation segments\nC. Thin plot\nD. Engaging storyline",
    "Answer": "Thin plot"
  },
  {
    "Question": "What element of the film is likely to enhance its audience attraction during the initial weekend?",
    "Options": "A. animation segments\nB. live-action scenes\nC. soundtrack\nD. special effects",
    "Answer": "animation segments"
  },
  {
    "Question": "Who is responsible for stealing two diamonds from the Belgian museum?",
    "Options": "A. Uncle\nB. goon angad\nC. museum curator\nD. diamond dealer",
    "Answer": "goon angad"
  },
  {
    "Question": "In which song does a dancer perform alongside Bruna Abdullah?",
    "Options": "A. Rahem Kare\nB. Chura Liya Hai Tumne Jo Dil Ko\nC. Tum Hi Ho\nD. Pehla Nasha",
    "Answer": "Rahem Kare"
  }
]