[
    {
        "Question": "Is 'Lage Raho Munna Bhai' a sequel to 'Munna Bhai M.B.B.S.'?",
        "Answer": "Yes"
    },
    {
        "Question": "Is Asthana's laugh a memorable part of the sequel to Munna Bhai M.B.B.S.?",
        "Answer": "Yes"
    },
    {
        "Question": "Is Gandhi a significant figure in the movie 'Munna Bhai M.B.B.S.'?",
        "Answer": "No"
    },
    {
        "Question": "Is the chaiwala boy connected to the production of *Munna Bhai M.B.B.S.*?",
        "Answer": "No"
    },
    {
        "Question": "Is 'Lage Raho Munna Bhai' a sequel to 'Munna Bhai M.B.B.S.'?",
        "Answer": "Yes"
    },
    {
        "Question": "Is 'Lage Raho Munna Bhai' a sequel to 'Munna Bhai M.B.B.S.'?",
        "Answer": "Yes"
    },
    {
        "Question": "Is 'Lage Raho Munna Bhai' a sequel to 'Munna Bhai M.B.B.S.'?",
        "Answer": "Yes"
    },
    {
        "Question": "Is Asthana's laugh featured in the film series that includes 'Munna Bhai M.B.B.S.'?",
        "Answer": "Yes."
    },
    {
        "Question": "Does *Lage Raho Munna Bhai* aim to revive interest in Gandhi?",
        "Answer": "Yes"
    },
    {
        "Question": "Did the production of 'Lage Raho Munna Bhai' involve an incident with a chaiwala boy?",
        "Answer": "Yes."
    },
    {
        "Question": "Is 'Lage Raho Munna Bhai' a sequel to 'Munna Bhai M.B.B.S.'?",
        "Answer": "Yes"
    },
    {
        "Question": "Is 'Lage Raho Munna Bhai' a sequel to 'Munna Bhai M.B.B.S.'?",
        "Answer": "Yes"
    },
    {
        "Question": "Is 'Lage Raho Munna Bhai' a sequel to 'Munna Bhai M.B.B.S.'?",
        "Answer": "Yes"
    },
    {
        "Question": "Does the character Asthana's laugh appear in the film Munna Bhai M.B.B.S.?",
        "Answer": "Yes"
    },
    {
        "Question": "Did Lage Raho Munna Bhai aim to revive interest in Gandhi?",
        "Answer": "Yes"
    },
    {
        "Question": "Did the production of *Lage Raho Munna Bhai* involve an incident with a chaiwala boy?",
        "Answer": "Yes."
    },
    {
        "Question": "Is 'Lage Raho Munna Bhai' a sequel to 'Munna Bhai M.B.B.S.'?",
        "Answer": "Yes"
    },
    {
        "Question": "Did the production team face resource shortages while making Lage Raho Munna Bhai?",
        "Answer": "Yes"
    },
    {
        "Question": "Is Lage Raho Munna Bhai a sequel to Munna Bhai M.B.B.S.?",
        "Answer": "Yes"
    },
    {
        "Question": "Is Lage Raho Munna Bhai a sequel to Munna Bhai M.B.B.S.?",
        "Answer": "Yes"
    },
    {
        "Question": "Is Lage Raho Munna Bhai a sequel to Munna Bhai M.B.B.S.?",
        "Answer": "Yes"
    }
]